tblock/__init__.py
tblock/__main__.py
tblock/cli.py
tblock/compat.py
tblock/config.py
tblock/const.py
tblock/exceptions.py
tblock/filters.py
tblock/hosts.py
tblock/rules.py
tblock/style.py
tblock/utils.py
tblock/argumentor/__init__.py
tblock/argumentor/exceptions.py
tblock/converter/__init__.py
tblock/converter/__main__.py
tblock/converter/syntaxtools.py
tblock/daemon/__init__.py
tblock/daemon/__main__.py
tblock-2.7.5.dist-info/LICENSE
tblock-2.7.5.dist-info/METADATA
tblock-2.7.5.dist-info/WHEEL
tblock-2.7.5.dist-info/entry_points.txt
tblock-2.7.5.dist-info/top_level.txt
tblock-2.7.5.dist-info/RECORD
